[
    {
        "measurement_type": "AUTOMATED_TEST",
        "child_of": [
            "103246e1-bcdf-5b6e-a8dc-4c7e81b91141"
        ],
        "measurement_id": "measurement.tacc.0xDEADBEEF"
    },
    {
        "measurement_type": "AUTOMATED_TEST",
        "child_of": [
            "103246e1-bcdf-5b6e-a8dc-4c7e81b91141"
        ],
        "measurement_id": "measurement.tacc.0xDEADBEF0"
    },
    {
        "measurement_type": "AUTOMATED_TEST",
        "child_of": [
            "103246e1-bcdf-5b6e-a8dc-4c7e81b91141"
        ],
        "measurement_id": "measurement.tacc.0xDEADBEF1"
    }
]
